<?xml version="1.0" encoding="utf-8" standalone="no"?>
<l10n>
    <texts>
        <text name="cco_apply_blocked_rule_not_saved" text="Application bloquée. Règle non enregistrée."/>
        <text name="cco_apply_failed" text="Échec de l'application."/>
        <text name="cco_apply_failed_backend" text="Échec de l'application : backend CCO indisponible."/>
        <text name="cco_backend_unavailable" text="Le backend CropControlOverride n'est pas disponible."/>
        <text name="cco_blocked_fields_header" text="Parcelle      Culture          Taille ha   Candidat         Raison"/>
        <text name="cco_blocked_npc_fields_count" text="Parcelles NPC bloquées : %d"/>
        <text name="cco_blocked_npc_fields_zero" text="Parcelles NPC bloquées : 0"/>
        <text name="cco_button_apply" text="APPLIQUER"/>
        <text name="cco_button_confirm_reset" text="CONFIRMER LA RÉINITIALISATION"/>
        <text name="cco_button_discard" text="IGNORER"/>
        <text name="cco_button_force_apply" text="APPLIQUER DE FORCE"/>
        <text name="cco_button_load_defaults" text="CHARGER LES PARAMÈTRES PAR DÉFAUT"/>
        <text name="cco_button_next_tab" text="ONGLET SUIVANT"/>
        <text name="cco_button_prev_tab" text="ONGLET PRÉCÉDENT"/>
        <text name="cco_button_reset_blocked_dryrun" text="RÉINIT. BLOQUÉ (TEST)"/>
        <text name="cco_button_regenerate_npc_preview" text="PRÉVISUALISER LA RÉGÉNÉRATION PNJ"/>
        <text name="cco_button_confirm_npc_regeneration" text="CONFIRMER LA RÉGÉNÉRATION PNJ"/>
        <text name="cco_regeneration_ui_help" text="Prévisualise et régénère tous les champs non possédés selon les règles de culture, les stades saisonniers et les pondérations de réensemencement."/>
        <text name="cco_button_save_defaults" text="ENREG. PARAMÈTRES PAR DÉFAUT DANS CONFIG.XML"/>
        <text name="cco_checked_fields_line" text="Parcelles vérifiées : %d"/>
        <text name="cco_cleanup_console_alternatives" text="Alternatives console disponibles : ccoScanBlocked, ccoResetBlocked dryrun, ccoResetBlocked."/>
        <text name="cco_cleanup_step_1" text="1. Utilisez PORTÉE RÉINIT. pour choisir TOUT, une culture ou une parcelle individuelle."/>
        <text name="cco_cleanup_step_2" text="2. Lancez RÉINIT. BLOQUÉ (TEST) avant de modifier l'état de la sauvegarde."/>
        <text name="cco_cleanup_step_3" text="3. Utilisez CONFIRMER LA RÉINIT. uniquement lorsque le résultat du test semble correct."/>
        <text name="cco_column_crop" text="Culture"/>
        <text name="cco_column_crop_type" text="Type de culture"/>
        <text name="cco_column_loaded" text="Chargée"/>
        <text name="cco_column_max_field" text="Max parcelle"/>
        <text name="cco_column_npc" text="NPC"/>
        <text name="cco_column_player" text="Joueur"/>
        <text name="cco_column_status" text="Statut"/>
        <text name="cco_confirm_reset_available" text="CONFIRMER LA RÉINIT. est maintenant disponible pour scope=%s resetMode=%s. Cela appliquera le mode de réinitialisation sélectionné."/>
        <text name="cco_defaults_readonly_admin" text="Les paramètres par défaut CCO sont en lecture seule pour les clients distants en multijoueur. Connectez-vous en tant qu'admin/master du serveur pour les modifier."/>
        <text name="cco_defaults_readonly_remote" text="Les paramètres par défaut CCO sont en lecture seule pour les clients distants en multijoueur."/>
        <text name="cco_dialog_test_body" text="Si vous pouvez lire ceci, l'écran GUI personnalisé CCO s'affiche correctement. Cet écran remplace l'approche InfoDialog expérimentale utilisée dans les versions alpha.11-alpha.13."/>
        <text name="cco_dryrun_complete" text="Test terminé."/>
        <text name="cco_dryrun_failed" text="Échec du test : %s"/>
        <text name="cco_dryrun_result_heading" text="RÉSULTAT DU TEST"/>
        <text name="cco_edit_rejected_not_admin" text="Modification CCO refusée : ce joueur n'est pas connecté en tant qu'admin/master du serveur."/>
        <text name="cco_empty_blockedrules" text="Aucune culture n'est actuellement désactivée pour l'usage par les NPC."/>
        <text name="cco_empty_disabled" text="Aucune culture désactivée n'est configurée pour cette sauvegarde."/>
        <text name="cco_empty_limited" text="Aucune culture limitée en taille n'est configurée pour cette sauvegarde."/>
        <text name="cco_empty_matching_rules" text="Aucune règle de culture correspondante."/>
        <text name="cco_empty_rules" text="Aucune règle de culture configurée ne correspond à cette vue."/>
        <text name="cco_empty_undiscovered" text="Toutes les cultures configurées sont actuellement chargées sur cette carte/sauvegarde."/>
        <text name="cco_failed_template_backup" text="Échec de la création de la sauvegarde du modèle ; config.xml n'a pas été modifié."/>
        <text name="cco_failed_to_save_rule" text="Échec de l'enregistrement de la règle."/>
        <text name="cco_failed_write_defaults_per_save" text="Échec de l'écriture des paramètres par défaut du modèle dans le XML actif par sauvegarde."/>
        <text name="cco_failed_write_template" text="Échec de l'écriture du modèle config.xml."/>
        <text name="cco_force_apply_hint" text="Cliquez sur APPLIQUER DE FORCE pour enregistrer quand même."/>
        <text name="cco_gui_subtitle" text="Éditeur des regles des cultures | Appliquer écrit le XML par sauvegarde | Charger les paramètres importe config.xml"/>
        <text name="cco_heading_actions" text="ACTIONS"/>
        <text name="cco_heading_active_config" text="CONFIGURATION ACTIVE"/>
        <text name="cco_heading_blocked_npc_field_details" text="DÉTAILS DES PARCELLES NPC BLOQUÉES"/>
        <text name="cco_heading_config_files" text="FICHIERS DE CONFIGURATION"/>
        <text name="cco_heading_config_hierarchy" text="HIÉRARCHIE DE CONFIGURATION"/>
        <text name="cco_heading_crop_rules" text="RÈGLES DES CULTURES"/>
        <text name="cco_heading_editing" text="ÉDITION"/>
        <text name="cco_heading_gui_cleanup" text="NETTOYAGE GUI"/>
        <text name="cco_heading_navigation" text="NAVIGATION"/>
        <text name="cco_heading_notice" text="AVIS"/>
        <text name="cco_heading_policy_summary" text="RÉSUMÉ DES REGLES"/>
        <text name="cco_heading_policy_terms" text="TERMES DES REGLES"/>
        <text name="cco_heading_save_validation" text="VALIDATION DE LA SAUVEGARDE"/>
        <text name="cco_heading_table_columns" text="COLONNES DU TABLEAU"/>
        <text name="cco_heading_validation_cleanup" text="NETTOYAGE DE VALIDATION"/>
        <text name="cco_help_cleanup_console" text="Alternatives console disponibles : ccoScanBlocked et ccoResetBlocked dryrun."/>
        <text name="cco_help_cleanup_dryrun" text="Lancez d'abord RÉINIT. BLOQUÉ (TEST). Cela ne modifie pas l'état de la sauvegarde."/>
        <text name="cco_help_cleanup_scope" text="Utilisez PORTÉE RÉINIT. pour alterner entre les cibles de nettoyage TOUT, CULTURE et PARCELLE."/>
        <text name="cco_help_column_loaded" text="Chargée : indique si la culture existe sur la carte/sauvegarde active."/>
        <text name="cco_help_column_max_field" text="Max parcelle : taille maximale réelle d'une parcelle NPC. Les valeurs sont stockées en hectares ; les acres sont affichés à titre indicatif."/>
        <text name="cco_help_column_npc" text="NPC autorisé : indique si les NPC peuvent planter la culture, ou si le paramètre par défaut de la carte est utilisé."/>
        <text name="cco_help_column_player" text="Joueur autorisé : indique si la culture est disponible selon les règles des cultures."/>
        <text name="cco_help_config_load_defaults" text="CHARGER LES PARAMÈTRES PAR DÉFAUT importe config.xml dans cette sauvegarde et écrase le XML actif par sauvegarde."/>
        <text name="cco_help_config_save_defaults" text="ENREG. PARAMÈTRES PAR DÉFAUT exporte toutes les règles actives de la sauvegarde vers config.xml et crée une sauvegarde."/>
        <text name="cco_help_config_savegame" text="saves/savegameX.xml est le fichier de règles actif pour la sauvegarde actuelle."/>
        <text name="cco_help_config_template" text="config.xml est le fichier de règles modèle/par défaut."/>
        <text name="cco_help_editing_all_rules" text="Utilisez TOUTES LES RÈGLES pour sélectionner une culture et préparer les modifications dans le panneau droit."/>
        <text name="cco_help_editing_apply" text="APPLIQUER écrit les modifications sûres dans le XML actif par sauvegarde."/>
        <text name="cco_help_editing_discard" text="IGNORER réinitialise les valeurs préparées pour la culture sélectionnée."/>
        <text name="cco_help_editing_force_apply" text="APPLIQUER DE FORCE enregistre délibérément une règle qui crée des parcelles NPC bloquées."/>
        <text name="cco_help_navigation_back" text="Utilisez RETOUR ou ÉCHAP pour fermer l'écran CCO."/>
        <text name="cco_help_navigation_tabs" text="Utilisez les en-têtes d'onglets ou ONGLET PRÉCÉDENT / ONGLET SUIVANT pour changer de section."/>
        <text name="cco_help_term_blocked" text="Parcelles NPC bloquées : parcelles NPC existantes qui violent actuellement la politique active."/>
        <text name="cco_help_term_disabled" text="Désactivée : la culture n'est pas disponible selon les règles des cultures."/>
        <text name="cco_help_term_not_loaded" text="Non chargée : la règle est conservée, mais la culture n'est pas présente sur cette carte/sauvegarde."/>
        <text name="cco_help_term_npc_disabled" text="NPC désactivé : les NPC ne devraient pas planter cette culture. Les cultures globalement désactivées sont également considérées comme désactivées pour les NPC."/>
        <text name="cco_help_term_size_limited" text="Taille limitée : les NPC peuvent planter la culture uniquement en dessous de la limite d'hectares configurée."/>
        <text name="cco_help_title" text="AIDE CROP CONTROL OVERRIDE"/>
        <text name="cco_label_loaded_on_map" text="Chargée sur la carte"/>
        <text name="cco_label_max_field_ha" text="Max parcelle (ha) 1 ha = 2,47 ac"/>
        <text name="cco_label_npc_permitted" text="NPC autorisé"/>
        <text name="cco_label_player_permitted" text="Joueur autorisé"/>
        <text name="cco_label_reset_npc_fields" text="Nettoyage des parcelles existantes"/>
        <text name="cco_label_rule_status" text="Statut de la règle"/>
        <text name="cco_load_defaults_failed" text="Échec du chargement des paramètres par défaut."/>
        <text name="cco_load_defaults_failed_detail" text="Échec du chargement des paramètres par défaut : %s"/>
        <text name="cco_loaded_template_into_save" text="Modèle config.xml chargé dans la config active de la sauvegarde : %s"/>
        <text name="cco_loaded_template_no_save" text="Modèle config.xml chargé. Aucun contexte de sauvegarde n'était disponible, donc aucun XML par sauvegarde n'a été écrit."/>
        <text name="cco_mode_title_blockedrules" text="Règles de cultures désactivées pour les NPC"/>
        <text name="cco_mode_title_disabled" text="Règles de cultures désactivées"/>
        <text name="cco_mode_title_limited" text="Règles de cultures NPC limitées en taille"/>
        <text name="cco_mode_title_rules" text="Toutes les règles de culture configurées"/>
        <text name="cco_mode_title_undiscovered" text="Configurées mais non chargées sur cette carte"/>
        <text name="cco_more_blocked_fields" text="... %d autre(s) parcelle(s) NPC bloquée(s). Utilisez ccoScanBlocked pour la liste complète dans la console."/>
        <text name="cco_mp_event_failed" text="Événement multijoueur CCO échoué : %s"/>
        <text name="cco_no_blocked_npc_fields" text="Aucune parcelle NPC bloquée n'a été détectée avec la politique culturale actuelle."/>
        <text name="cco_no_crop_selected" text="Aucune culture sélectionnée."/>
        <text name="cco_no_crop_selected_short" text="Aucune culture sélectionnée"/>
        <text name="cco_no_staged_changes" text="Aucune modification préparée."/>
        <text name="cco_no_staged_rule_selected" text="Aucune règle préparée sélectionnée."/>
        <text name="cco_none" text="AUCUN"/>
        <text name="cco_not_loaded_hidden" text="NON CHARGÉE : CACHÉE"/>
        <text name="cco_not_loaded_lower" text="non chargée"/>
        <text name="cco_not_loaded_shown" text="NON CHARGÉE : AFFICHÉE"/>
        <text name="cco_npc_fields_line" text="Parcelles NPC :     %d"/>
        <text name="cco_page_end_hint" text="Page %d/%d. Fin de la liste."/>
        <text name="cco_page_next_hint" text="Page %d/%d. Utilisez ccoGui %s %d pour la page suivante."/>
        <text name="cco_panel_selected_crop" text="CULTURE SÉLECTIONNÉE"/>
        <text name="cco_panel_staged_rule_values" text="VALEURS DE RÈGLE PRÉPARÉES"/>
        <text name="cco_player_fields_line" text="Parcelles joueur :  %d"/>
        <text name="cco_read_only" text="Lecture seule"/>
        <text name="cco_readonly_server_rules" text="Règles du serveur en lecture seule. Seul le serveur/hôte peut modifier les paramètres CCO."/>
        <text name="cco_remote_reset_readonly" text="Clients distants en lecture seule en multijoueur. Les actions de réinitialisation ne peuvent être lancées que par le serveur/hôte."/>
        <text name="cco_requested_rules_from_server" text="Règles CCO demandées au serveur."/>
        <text name="cco_reset_complete" text="Réinitialisation terminée."/>
        <text name="cco_reset_failed" text="Échec de la réinitialisation : %s"/>
        <text name="cco_reset_mode_cultivated" text="CULTIVÉE"/>
        <text name="cco_reset_mode_cultivated_button" text="MODE RÉINIT. : CULTIVÉE"/>
        <text name="cco_reset_mode_prefix" text="MODE RÉINIT. : %s"/>
        <text name="cco_reset_mode_reseed_seasonal" text="RESEMIS SAISONNIER"/>
        <text name="cco_reset_readonly_admin" text="La réinitialisation CCO est en lecture seule pour les clients distants en multijoueur. Connectez-vous en tant qu'admin/master du serveur pour modifier les parcelles."/>
        <text name="cco_reset_readonly_remote" text="La réinitialisation CCO est en lecture seule pour les clients distants en multijoueur."/>
        <text name="cco_reset_result_heading" text="RÉSULTAT DE LA RÉINITIALISATION"/>
        <text name="cco_reset_scope_all" text="PORTÉE RÉINIT. : TOUT"/>
        <text name="cco_reset_scope_prefix" text="PORTÉE RÉINIT. : %s"/>
        <text name="cco_rule_saved_info" text="La règle de culture sélectionnée a été enregistrée dans le XML CCO actif et les règles ont été réappliquées."/>
        <text name="cco_rule_saved_validation_passed" text="Règle enregistrée. Validation réussie."/>
        <text name="cco_rule_saved_validation_warning" text="Règle enregistrée. Avertissement de validation."/>
        <text name="cco_rule_rejected_server" text="Le serveur a rejeté la règle."/>
        <text name="cco_rule_saved_server" text="Règle enregistrée par le serveur."/>
        <text name="cco_rule_sent_server_validation" text="La règle a été envoyée au serveur dédié pour validation. La modification préparée sera conservée jusqu'à la réponse du serveur."/>
        <text name="cco_rules_readonly_admin" text="Les règles CCO sont en lecture seule pour les clients distants en multijoueur. Connectez-vous en tant qu'admin/master du serveur pour les modifier."/>
        <text name="cco_rules_readonly_remote" text="Les règles CCO sont en lecture seule pour les clients distants en multijoueur."/>
        <text name="cco_save_defaults_failed" text="Échec de l'enregistrement des paramètres par défaut."/>
        <text name="cco_saved_defaults" text="Paramètres par défaut enregistrés."/>
        <text name="cco_saved_rules_to_template" text="Règles actives actuelles enregistrées dans le modèle config.xml. Les fichiers XML existants par sauvegarde n'ont pas été écrasés"/>
        <text name="cco_scope_all" text="TOUT"/>
        <text name="cco_scope_crop_prefix" text="CULTURE : %s"/>
        <text name="cco_select_crop_info" text="Sélectionnez une ligne de culture, puis utilisez les contrôles de sélecteur/valeur pour préparer les modifications."/>
        <text name="cco_sent_operation_request" text="Requête CCO %s envoyée au serveur."/>
        <text name="cco_server_sync_open_again" text="Rouvrez CCO une fois l'instantané du serveur reçu, ou utilisez ccoReload pour redemander les règles du serveur."/>
        <text name="cco_server_sync_remote_client" text="Ceci est un client distant en multijoueur. Les fichiers config.xml et savegame?.xml locaux CCO ne sont pas utilisés dans cette session."/>
        <text name="cco_settings_synced_server" text="Paramètres CCO synchronisés depuis le serveur."/>
        <text name="cco_shown_matching_rules" text="Affiché %d-%d sur %d règle(s) correspondante(s)."/>
        <text name="cco_shown_zero_matching_rules" text="Affiché 0 sur 0 règle(s) correspondante(s)."/>
        <text name="cco_stage_changes_info" text="Utilisez les contrôles de sélecteur/valeur pour préparer les modifications, puis APPLIQUER."/>
        <text name="cco_staged_changes_ready" text="Modifications préparées prêtes. Appliquer enregistrera le XML."/>
        <text name="cco_status_actions_apply" text="APPLIQUER / APPLIQUER DE FORCE écrit les modifications de culture préparées dans cette sauvegarde uniquement."/>
        <text name="cco_status_actions_load_defaults" text="CHARGER LES PARAMÈTRES PAR DÉFAUT importe le modèle config.xml dans cette sauvegarde et écrase les règles actives par sauvegarde."/>
        <text name="cco_status_actions_save_defaults" text="ENREG. PARAMÈTRES PAR DÉFAUT exporte les règles actuelles de la sauvegarde vers le modèle config.xml."/>
        <text name="cco_status_allowed" text="AUTORISÉ"/>
        <text name="cco_status_checked_fields" text="Parcelles vérifiées :         %d"/>
        <text name="cco_status_cleanup_dryrun" text="Utilisez d'abord RÉINIT. BLOQUÉ (TEST), puis CONFIRMER LA RÉINIT. si le résultat semble correct. Le test signale également un candidat de resemis pour le mode resemis futur."/>
        <text name="cco_status_cleanup_scope" text="Utilisez PORTÉE RÉINIT. pour choisir TOUT, CULTURE ou PARCELLE."/>
        <text name="cco_status_config_hierarchy_apply" text="APPLIQUER / APPLIQUER DE FORCE écrit la règle sélectionnée dans le XML actif par sauvegarde."/>
        <text name="cco_status_config_hierarchy_per_save" text="Les fichiers XML existants par sauvegarde ne sont pas écrasés par ENREG. PARAMÈTRES PAR DÉFAUT."/>
        <text name="cco_status_config_hierarchy_save_defaults" text="ENREG. PARAMÈTRES PAR DÉFAUT écrit l'ensemble complet des règles actives dans config.xml pour une utilisation future/par défaut."/>
        <text name="cco_status_configured_rules_count" text="Règles configurées :       %d"/>
        <text name="cco_status_disabled" text="DÉSACTIVÉ"/>
        <text name="cco_status_disabled_crops_count" text="Cultures désactivées :         %d"/>
        <text name="cco_status_loaded_rules_count" text="Règles de culture chargées :      %d"/>
        <text name="cco_status_navigation_help" text="Utilisez les onglets du haut, ou ONGLET PRÉCÉDENT / ONGLET SUIVANT, pour naviguer entre les sections. Utilisez RETOUR pour fermer."/>
        <text name="cco_status_not_loaded" text="NON CHARGÉE"/>
        <text name="cco_status_not_loaded_count" text="Non chargée sur la carte :      %d"/>
        <text name="cco_status_npc_disabled" text="NPC DÉSACTIVÉ"/>
        <text name="cco_status_npc_disabled_count" text="Cultures désactivées NPC :      %d"/>
        <text name="cco_status_npc_fields" text="Parcelles NPC :             %d"/>
        <text name="cco_status_player_fields" text="Parcelles joueur :          %d"/>
        <text name="cco_status_size_limited" text="TAILLE LIMITÉE"/>
        <text name="cco_status_size_limited_count" text="Cultures limitées en taille :     %d"/>
        <text name="cco_status_unknown" text="INCONNU"/>
        <text name="cco_status_validation_status" text="Statut :                 %s"/>
        <text name="cco_tab_all_rules" text="TOUTES LES RÈGLES"/>
        <text name="cco_tab_disabled" text="DÉSACTIVÉES"/>
        <text name="cco_tab_help" text="AIDE"/>
        <text name="cco_tab_npc_disabled" text="NPC DÉSACTIVÉ"/>
        <text name="cco_tab_size_limited" text="TAILLE LIMITÉE"/>
        <text name="cco_tab_summary" text="RÉSUMÉ"/>
        <text name="cco_tab_validation" text="VALIDATION"/>
        <text name="cco_template_config_updated" text="Modèle de config mis à jour."/>
        <text name="cco_title" text="Crop Control Override"/>
        <text name="cco_title_blocked_fields" text="Crop Control Override - Parcelles bloquées"/>
        <text name="cco_title_blocked_rules" text="Crop Control Override - Règles bloquées"/>
        <text name="cco_title_configured_rules" text="Crop Control Override - Règles configurées"/>
        <text name="cco_title_dialog_test" text="Crop Control Override - Test de dialogue"/>
        <text name="cco_title_disabled_crops" text="Crop Control Override - Cultures désactivées"/>
        <text name="cco_title_gui_help" text="Crop Control Override - Aide GUI"/>
        <text name="cco_title_help" text="Crop Control Override - Aide"/>
        <text name="cco_title_npc_disabled_rules" text="Crop Control Override - Règles NPC désactivées"/>
        <text name="cco_title_server_sync_upper" text="CROP CONTROL OVERRIDE - SYNCHRO SERVEUR"/>
        <text name="cco_title_size_limited_crops" text="Crop Control Override - Cultures limitées en taille"/>
        <text name="cco_title_summary" text="Crop Control Override - Résumé"/>
        <text name="cco_title_undiscovered_rules" text="Crop Control Override - Règles non découvertes"/>
        <text name="cco_title_upper" text="CROP CONTROL OVERRIDE"/>
        <text name="cco_title_validation" text="Crop Control Override - Validation"/>
        <text name="cco_title_waiting_server_rules" text="Crop Control Override - En attente des règles du serveur"/>
        <text name="cco_unknown_topic" text="Sujet inconnu : %s"/>
        <text name="cco_validation_failed_count" text="ÉCHEC - %s parcelle(s) NPC problématique(s)"/>
        <text name="cco_validation_found_blocked" text="La validation a détecté des parcelles NPC bloquées. Consultez l'onglet VALIDATION avant d'utiliser ccoResetBlocked dryrun."/>
        <text name="cco_validation_found_blocked_count" text="La validation a détecté %s parcelle(s) NPC bloquée(s). Consultez l'onglet VALIDATION avant d'utiliser ccoResetBlocked dryrun."/>
        <text name="cco_validation_line_failed" text="Validation :     ÉCHEC"/>
        <text name="cco_validation_line_pass" text="Validation :     RÉUSSI"/>
        <text name="cco_validation_pass" text="RÉUSSI"/>
        <text name="cco_value_map_default" text="Par défaut de la carte"/>
        <text name="cco_value_no" text="Non"/>
        <text name="cco_value_off" text="off"/>
        <text name="cco_value_on" text="on"/>
        <text name="cco_value_yes" text="Oui"/>
        <text name="cco_viewing_server_rules" text="Affichage des règles CCO côté serveur. Les clients distants ne peuvent pas modifier ou écrire de XML local en multijoueur."/>
        <text name="cco_waiting_mp_connection_send" text="En attente de la connexion au serveur multijoueur avant d'envoyer la requête CCO %s."/>
        <text name="cco_waiting_mp_connection_sync" text="En attente de la connexion au serveur multijoueur avant de synchroniser les règles CCO."/>
        <text name="cco_waiting_server_apply" text="En attente de la confirmation du serveur..."/>
        <text name="cco_waiting_server_reset" text="En attente de la confirmation du serveur dédié..."/>
        <text name="cco_waiting_server_validation" text="En attente de la validation du serveur dédié..."/>
        <text name="cco_waiting_server_rules" text="En attente des règles CCO du serveur."/>
        <text name="input_CCO_OPEN_GUI" text="Ouvrir Crop Control Override"/>
        <text name="cco_label_reseed_weight" text="Poids de ressemis (0-5)"/>
        <text name="cco_sowing_not_permitted" text="Crop Control Override : Le semis de %s n’est pas autorisé."/>
    </texts>
</l10n>
